kisters/water/rest_client/__init__.py
kisters/water/rest_client/auth.py
kisters/water/rest_client/rest_client.py
kisters.water.rest_client-0.0.8.dist-info/LICENSE
kisters.water.rest_client-0.0.8.dist-info/METADATA
kisters.water.rest_client-0.0.8.dist-info/WHEEL
kisters.water.rest_client-0.0.8.dist-info/top_level.txt
kisters.water.rest_client-0.0.8.dist-info/RECORD
