Metadata-Version: 2.1
Name: kisters.water.rest-client
Version: 0.0.8
Summary: Authenticated REST Client for the Kisters Water ecosystem
Home-page: https://gitlab.com/kisters/water/rest_client
Author: Jesse VanderWees
Author-email: jesse.vanderwees@kisters-bv.nl
License: UNKNOWN
Platform: UNKNOWN
Classifier: Programming Language :: Python :: 3.6
Classifier: Programming Language :: Python :: 3.7
Classifier: Programming Language :: Python :: 3.8
Classifier: License :: OSI Approved :: GNU Lesser General Public License v2 or later (LGPLv2+)
Classifier: Operating System :: OS Independent
Requires-Dist: requests
Requires-Dist: msgpack
Provides-Extra: test
Requires-Dist: pytest ; extra == 'test'
